portiaitempipelineutils/__init__.py
portiaitempipelineutils/portiaitempipelineutils.py
PortiaItemPipelineUtils-0.0.1.dist-info/LICENSE
PortiaItemPipelineUtils-0.0.1.dist-info/METADATA
PortiaItemPipelineUtils-0.0.1.dist-info/WHEEL
PortiaItemPipelineUtils-0.0.1.dist-info/top_level.txt
PortiaItemPipelineUtils-0.0.1.dist-info/RECORD
